saraki/__init__.py
saraki/api.py
saraki/app.py
saraki/auth.py
saraki/config.py
saraki/endpoints.py
saraki/errors.py
saraki/exc.py
saraki/model.py
saraki/testing.py
saraki/utility.py
saraki-0.1.0a0.dist-info/METADATA
saraki-0.1.0a0.dist-info/RECORD
saraki-0.1.0a0.dist-info/WHEEL
saraki-0.1.0a0.dist-info/top_level.txt
