Metadata-Version: 2.1
Name: saraki
Version: 0.1.0a0
Summary: A web application helper
Home-page: https://github.com/mbarakaja/saraki
Author: José María Domínguez Moreno
Author-email: miso.0b11@gmail.com
License: MIT license
Keywords: saraki
Platform: UNKNOWN
Classifier: Development Status :: 2 - Pre-Alpha
Classifier: Intended Audience :: Developers
Classifier: License :: OSI Approved :: MIT License
Classifier: Natural Language :: English
Classifier: Programming Language :: Python :: 3.6
Requires-Dist: flask (>=1.0.2)
Requires-Dist: sqlalchemy (>=1.2.10)
Requires-Dist: flask-sqlalchemy (>=2.3.2)
Requires-Dist: pyjwt (>=1.6.4)
Requires-Dist: cerberus (>=1.2)
Requires-Dist: passlib (>=1.7.1)
Requires-Dist: psycopg2-binary (>=2.7.5)
Requires-Dist: bcrypt (>=3.1.4)
